{"id":"T9/G","dependencies":[{"name":"/Users/angelawang/Documents/GitHub/storytelling-homework-13-responsive-scrollytelling/package.json","includedInParent":true,"mtime":1540592112452}],"generated":{"js":"module.exports=\"/storytelling-homework-13-responsive-storytelling/0aa8ad1185fc61808a178adb6809c434.csv\";","map":{"mappings":[{"source":"0","name":"module","original":{"line":1,"column":0},"generated":{"line":1,"column":0}},{"source":"0","name":"exports","original":{"line":1,"column":7},"generated":{"line":1,"column":7}},{"source":"0","original":{"line":1,"column":17},"generated":{"line":1,"column":15}}],"sources":{},"lineCount":null}},"hash":"7cf99bdffb261ad361665f14e40e212f","cacheData":{"env":{}}}